tagging_autocomplete/__init__.py
tagging_autocomplete/models.py
tagging_autocomplete/urls.py
tagging_autocomplete/views.py
tagging_autocomplete/widgets.py
tagging_autocomplete/static/tagging_autocomplete/css/tagging_autocomplete.css
tagging_autocomplete/static/tagging_autocomplete/css/base/jquery.ui.all.css
tagging_autocomplete/static/tagging_autocomplete/css/base/jquery.ui.autocomplete.css
tagging_autocomplete/static/tagging_autocomplete/css/base/jquery.ui.base.css
tagging_autocomplete/static/tagging_autocomplete/css/base/jquery.ui.core.css
tagging_autocomplete/static/tagging_autocomplete/css/base/jquery.ui.theme.css
tagging_autocomplete/static/tagging_autocomplete/css/base/images/ui-bg_flat_0_aaaaaa_40x100.png
tagging_autocomplete/static/tagging_autocomplete/css/base/images/ui-bg_flat_75_ffffff_40x100.png
tagging_autocomplete/static/tagging_autocomplete/css/base/images/ui-bg_glass_55_fbf9ee_1x400.png
tagging_autocomplete/static/tagging_autocomplete/css/base/images/ui-bg_glass_65_ffffff_1x400.png
tagging_autocomplete/static/tagging_autocomplete/css/base/images/ui-bg_glass_75_dadada_1x400.png
tagging_autocomplete/static/tagging_autocomplete/css/base/images/ui-bg_glass_75_e6e6e6_1x400.png
tagging_autocomplete/static/tagging_autocomplete/css/base/images/ui-bg_glass_95_fef1ec_1x400.png
tagging_autocomplete/static/tagging_autocomplete/css/base/images/ui-bg_highlight-soft_75_cccccc_1x100.png
tagging_autocomplete/static/tagging_autocomplete/css/base/images/ui-icons_222222_256x240.png
tagging_autocomplete/static/tagging_autocomplete/css/base/images/ui-icons_2e83ff_256x240.png
tagging_autocomplete/static/tagging_autocomplete/css/base/images/ui-icons_454545_256x240.png
tagging_autocomplete/static/tagging_autocomplete/css/base/images/ui-icons_888888_256x240.png
tagging_autocomplete/static/tagging_autocomplete/css/base/images/ui-icons_cd0a0a_256x240.png
tagging_autocomplete/static/tagging_autocomplete/js/jquery-1.6.2.min.js
django_tagging_autocomplete-0.5.1.dist-info/LICENSE
django_tagging_autocomplete-0.5.1.dist-info/METADATA
django_tagging_autocomplete-0.5.1.dist-info/WHEEL
django_tagging_autocomplete-0.5.1.dist-info/top_level.txt
django_tagging_autocomplete-0.5.1.dist-info/RECORD
