Metadata-Version: 2.1
Name: django-tagging-autocomplete
Version: 0.5.1
Summary: Autocompletion for django-tagging
Home-page: https://github.com/ludwiktrammer/django-tagging-autocomplete/
Author: Ludwik Trammer
Author-email: ludwik@gmail.com
License: UNKNOWN
Platform: UNKNOWN
Classifier: Development Status :: 4 - Beta
Classifier: Environment :: Web Environment
Classifier: Intended Audience :: Developers
Classifier: License :: OSI Approved :: MIT License
Classifier: Operating System :: OS Independent
Classifier: Programming Language :: Python
Classifier: Framework :: Django
